pdfgeneratorapi/__init__.py
pdfgeneratorapi/constants.py
pdfgeneratorapi/decorators.py
pdfgeneratorapi/exceptions.py
pdfgeneratorapi/response.py
pdfgeneratorapi/utils.py
pdfgeneratorapi/wrapper.py
pdfgeneratorapi-0.1.dist-info/LICENSE
pdfgeneratorapi-0.1.dist-info/METADATA
pdfgeneratorapi-0.1.dist-info/WHEEL
pdfgeneratorapi-0.1.dist-info/top_level.txt
pdfgeneratorapi-0.1.dist-info/RECORD
